MANIFEST.in
README.md
setup.py
frtg/__init__.py
frtg/app.py
frtg/routes.py
frtg.egg-info/PKG-INFO
frtg.egg-info/SOURCES.txt
frtg.egg-info/dependency_links.txt
frtg.egg-info/requires.txt
frtg.egg-info/top_level.txt
frtg/static/js/bundle.js
frtg/templates/index.html
test/test_api.py